LICENSE
MANIFEST.in
README.md
setup.py
proofread/__init__.py
proofread/base.py
proofread.egg-info/PKG-INFO
proofread.egg-info/SOURCES.txt
proofread.egg-info/dependency_links.txt
proofread.egg-info/not-zip-safe
proofread.egg-info/top_level.txt
proofread/contrib/__init__.py
proofread/contrib/django_proofread/__init__.py
proofread/contrib/django_proofread/models.py
proofread/contrib/django_proofread/tests.py
proofread/contrib/django_proofread/management/__init__.py
proofread/contrib/django_proofread/management/commands/__init__.py
proofread/contrib/django_proofread/management/commands/proofread.py
proofread/contrib/flask_proofread/__init__.py
proofread/contrib/flask_proofread/tests.py