Metadata-Version: 1.0
Name: proofread
Version: 0.1.2
Summary: Test your web app without writing tests!
Home-page: https://github.com/mattrobenolt/proofread
Author: Matt Robenolt
Author-email: matt@ydekproductions.com
License: BSD
Platform: UNKNOWN
Classifier: Framework :: Django
Classifier: Intended Audience :: Developers
Classifier: Intended Audience :: System Administrators
Classifier: Operating System :: OS Independent
Classifier: Topic :: Software Development
